Workbook
Name B_eq: WACC!$E$7
Name D: WACC!$E$12
Name debt_ratio: WACC!$E$14
Name E: WACC!$E$11
Name equity_ratio: WACC!$E$13
Name leverage: WACC!$E$14
Name MRP: WACC!$E$9
Name Rd: WACC!$E$16
Name Re: WACC!$E$6
Name Rf: WACC!$E$8
Name scenario: 'DCF '!$C$16
Name tax_shield: WACC!$E$17

Sheet DCF 
F1: 2021 | G1: 2022 | H1: 2023 | I1: 2024 | J1: 2025 | K1: 2026 | L1: 2027 | M1: 2028 | N1: 2029 | O1: 2030
B2: NETFLIX DCF MODEL
A4: X | B4: General
B6: Company Ticker | C6: NFLX
B7: Date | C7: =TODAY() -> 46257
B8: End of Fiscal Year | C8: 46387
B9: Share Price | C9: 78
B10: Intrinsic Value | C10: =O121 -> 72.773146
B11: Delta | C11: =C10/C9-1 -> -0.067010945
A13: X | B13: Assumptions
B15: Triggers | L15: 1 - Bearish Case | P15: 2- Street Case | U15: 3- Bullish Case
B16: Scenario | C16: 2 | L16: Rev g FY2026 % street | N16: 0.8 | U16: Rev g FY2026 % street | W16: 1.25
B17: WACC | C17: =CHOOSE(scenario,N26,Q26,W26) -> 0.083152446 | L17: Rev g FY2030 % street | N17: 0.9 | U17: Rev g FY2030 % base | W17: 1.4
B18: TGR | C18: =CHOOSE(scenario,N27,Q27,W27) -> 0.025 | L18: EBITDA % FY2026 | N18: 0.635 | U18: EBITDA growth FY2026 | W18: 0.682
L19: EBITDA % FY2030 | N19: 0.71 | U19: EBITDA growth FY2030 | W19: 0.744
L20: EBIT % FY2026 | N20: =AVERAGE(F38:J38) -> 0.23082125 | U20: EBIT % FY2026 | W20: 0.325
L21: EBIT % FY2030 | N21: 0.32 | U21: EBIT % FY2030 | W21: 0.38
L22: CapEx % sales | N22: 0.02 | U22: CapEx % sales | W22: 0.015
L23: Content Spend % FY 2026 | N23: =AVERAGE($H$94:$J$94) -> -0.38907529 | P23: Content Spend % FY 2026 | R23: -0.375 | U23: Content Spend % FY 2026 | W23: =$N$23 -> -0.38907529
L24: Content Spend % FY 2030 | N24: -0.38 | P24: Content Spend % FY 2030 | R24: -0.35 | U24: Content Spend % FY 2030 | W24: -0.33
L26: WACC | N26: =Q26+0.5% -> 0.088152446 | P26: WACC | Q26: =WACC!E19 -> 0.083152446 | U26: WACC | W26: =Q26-0.5% -> 0.078152446
L27: TGR | N27: =Q27-0.5% -> 0.02 | P27: TGR | Q27: 0.025 | U27: TGR | W27: =Q27+0.5% -> 0.03
A29: X | B29: Financials
B31: Revenue | F31: =IS!F2 -> 29698 | G31: =IS!E2 -> 31616 | H31: =IS!D2 -> 33723 | I31: =IS!C2 -> 38877 | J31: =IS!B2 -> 45274 | K31: =J31*(1+K32) -> 52065.1 | L31: 57249 | M31: 63123 | N31: =M31+(M31*N32) -> 69750.915 | O31: =N31+(N31*O32) -> 76028.497
B32: % growth | G32: =G31/F31-1 -> 0.064583474 | H32: =H31/G31-1 -> 0.066643472 | I32: =I31/H31-1 -> 0.15283338 | J32: =J31/I31-1 -> 0.16454459 | K32: 0.15 | L32: =K32+($O$32-$K$32)/($O$1-$K$1) -> 0.135 | M32: =L32+($O$32-$K$32)/($O$1-$K$1) -> 0.12 | N32: =M32+($O$32-$K$32)/($O$1-$K$1) -> 0.105 | O32: 0.09
B34: EBITDA | F34: =IS!F48 -> 18633 | G34: =IS!E48 -> 19996 | H34: =IS!D48 -> 21508 | I34: =IS!C48 -> 25922 | J34: =IS!B48 -> 30175 | K34: =SUM(K37+K46) -> 34492.795 | L34: =SUM(L37+L46) -> 39237.137 | M34: =SUM(M37+M46) -> 44345.632 | N34: =SUM(N37+N46) -> 46180.23 | O34: =SUM(O37+O46) -> 50842.565
B35: % sales | F35: =F34/F$31 -> 0.62741599 | G35: =G34/G$31 -> 0.63246457 | H35: =H34/H$31 -> 0.6377843 | I35: =I34/I$31 -> 0.66676956 | J35: =J34/J$31 -> 0.66649733 | K35: =K34/K$31 -> 0.6624936 | L35: =L34/L$31 -> 0.6853768 | M35: =M34/M$31 -> 0.70252732 | ... O35: =O34/O$31 -> 0.66873037
B37: EBIT | F37: =IS!F51 -> 6195 | G37: =IS!E51 -> 5633 | H37: =IS!D51 -> 6954 | I37: =IS!C51 -> 10292 | J37: =IS!B51 -> 13419 | K37: ='Q2'!O14 -> 16298 | L37: 19480 | M37: 22892 | N37: =N31*N38 -> 22884.429 | O37: =O31*O38 -> 25546.412
B38: % sales | F38: =F37/F$31 -> 0.20859991 | G38: =G37/G$31 -> 0.17816928 | H38: =H37/H$31 -> 0.20620941 | I38: =I37/I$31 -> 0.26473236 | J38: =J37/J$31 -> 0.29639528 | K38: =K37/K$31 -> 0.31303119 | L38: =L37/L31 -> 0.34026795 | M38: =M37/M31 -> 0.36265703 | N38: =AVERAGE(J38:M38) -> 0.32808786 | O38: =AVERAGE(K38:N38) -> 0.33601101
B40: Taxes | F40: =IS!F26 -> 724 | G40: =IS!E26 -> 772 | H40: =IS!D26 -> 797 | I40: =IS!C26 -> 1254 | J40: =IS!B26 -> 1741 | K40: =K37*K41 -> 2021.3167 | L40: =L37*L41 -> 2443.8276 | M40: =M37*M41 -> 2818.781 | N40: =N37*N41 -> 2856.8603 | O40: =O37*O41 -> 3204.4881
B41: % tax rate | F41: =F40/F37 -> 0.11686844 | G41: =G40/G37 -> 0.13704953 | H41: =H40/H37 -> 0.1146103 | I41: =I40/I37 -> 0.12184221 | J41: =J40/J37 -> 0.12974141 | K41: =AVERAGE(F41:J41) -> 0.12402238 | L41: =AVERAGE(G41:K41) -> 0.12545316 | M41: =AVERAGE(H41:L41) -> 0.12313389 | N41: =AVERAGE(I41:M41) -> 0.12483861 | O41: =AVERAGE(J41:N41) -> 0.12543789
A44: X | B44: Cash Flow Items
B46: D&A | F46: =CF!F7 -> 12439 | G46: =CF!E7 -> 14363 | H46: =CF!D7 -> 14554 | I46: =CF!C7 -> 15630 | J46: =CF!B7 -> 16756 | K46: =J46+(J46*'Q2'!R39) -> 18194.795 | L46: =K46+(K46*'Q2'!R39) -> 19757.137 | M46: =L46+(L46*'Q2'!R39) -> 21453.632 | N46: =M46+(M46*'Q2'!R39) -> 23295.801 | O46: =N46+(N46*'Q2'!R39) -> 25296.153
B47: % sales | F47: =F46/F31 -> 0.41884975 | G47: =G46/G31 -> 0.45429529 | H47: =H46/H31 -> 0.43157489 | I47: =I46/I31 -> 0.40203719 | J47: =J46/J31 -> 0.37010205 | K47: =K46/K31 -> 0.34946241 | L47: =L46/L31 -> 0.34510885 | M47: =M46/M31 -> 0.33987028 | ... O47: =O46/O31 -> 0.33271936
B48: % CapEx
B50: CapEX | F50: =CF!F30 -> -552 | G50: =CF!E30 -> -408 | H50: =CF!D30 -> -349 | I50: =CF!C30 -> -440 | J50: =CF!B30 -> -688 | K50: =-(415+(415*1.2)) -> -913 | L50: =(L31*L51) -> -1144.98 | M50: =(M31*M51) -> -1262.46 | N50: =(N31*N51) -> -1046.2637 | O50: =(O31*O51) -> -912.34197
B51: % sales | F51: =(F50/F31) -> -0.01858711 | G51: =(G50/G31) -> -0.012904858 | H51: =(H50/H31) -> -0.01034902 | I51: =(I50/I31) -> -0.011317746 | J51: =(J50/J31) -> -0.01519636 | K51: =-(K50/K31) -> 0.017535739 | L51: -0.02 | M51: -0.02 | N51: -0.015 | O51: -0.012
B53: Changes in WC | G53: 1754 | H53: -278 | I53: 1288 | J53: =SUM((BS!B19-BS!B50)-(BS!C19-BS!C50)) -> -306 | K53: =K31*K54 -> 958.07449 | L53: =L31*L54 -> 522.81393 | M53: =M31*M54 -> 850.66188 | N53: =N31*N54 -> 597.26253 | O53: =O31*O54 -> 942.23643
B54: % sales | G54: =G53/G31 -> 0.055478239 | H54: =H53/H31 -> -0.0082436319 | I54: =I53/I31 -> 0.033130128 | J54: =J53/J31 -> -0.0067588461 | K54: =AVERAGE(G54:J54) -> 0.018401472 | L54: =AVERAGE(H54:K54) -> 0.0091322806 | M54: =AVERAGE(I54:L54) -> 0.013476259 | N54: =AVERAGE(J54:M54) -> 0.0085627914 | O54: =AVERAGE(K54:N54) -> 0.012393201
A58: X | B58: DCF Model
B60: Revenue | F60: 29698 | G60: 31616 | H60: 33723 | I60: 38877 | J60: 45274 | K60: =J60*(1+K61) -> 52065.1 | L60: =K60*(1+L61) -> 59093.889 | M60: =L60*(1+M61) -> 66185.155 | N60: =M60*(1+N61) -> 73134.596 | O60: =N60*(1+O61) -> 79716.71
B61: % growth | G61: 0.064583474 | H61: 0.066643472 | I61: 0.15283338 | J61: 0.16454459 | K61: =CHOOSE(scenario, K62,K63,K64) -> 0.15 | L61: =CHOOSE(scenario, L62,L63,L64) -> 0.135 | M61: =CHOOSE(scenario, M62,M63,M64) -> 0.12 | N61: =CHOOSE(scenario, N62,N63,N64) -> 0.105 | O61: =CHOOSE(scenario, O62,O63,O64) -> 0.09
B62: Bear Case | K62: =K63*N16 -> 0.12 | L62: =K62+($O$62-$K$62)/($O$1-$K$1) -> 0.11025 | M62: =L62+($O$62-$K$62)/($O$1-$K$1) -> 0.1005 | N62: =M62+($O$62-$K$62)/($O$1-$K$1) -> 0.09075 | O62: =O63*N17 -> 0.081
B63: Street Case | K63: =K32 -> 0.15 | L63: =L32 -> 0.135 | M63: =M32 -> 0.12 | N63: =N32 -> 0.105 | O63: =O32 -> 0.09
B64: Bullish Case | K64: =K63*W16 -> 0.1875 | L64: =K64+($O$64-$K$64)/($O$1-$K$1) -> 0.172125 | M64: =L64+($O$64-$K$64)/($O$1-$K$1) -> 0.15675 | N64: =M64+($O$64-$K$64)/($O$1-$K$1) -> 0.141375 | O64: =O63*W17 -> 0.126
B66: EBITDA | F66: 18633 | G66: 19996 | H66: 21508 | I66: 25922 | J66: 30175 | K66: =K60*K67 -> 34492.795 | L66: =L60*L67 -> 40501.58 | M66: =M60*M67 -> 46496.88 | N66: =N60*N67 -> 48420.476 | O66: =O60*O67 -> 53308.985
B67: % sales | F67: =F66/F$60 -> 0.62741599 | G67: =G66/G$60 -> 0.63246457 | H67: =H66/H$60 -> 0.6377843 | I67: =I66/I$60 -> 0.66676956 | J67: =J66/J$60 -> 0.66649733 | K67: =CHOOSE(scenario, K68,K69,K70) -> 0.6624936 | L67: =CHOOSE(scenario, L68,L69,L70) -> 0.6853768 | M67: =CHOOSE(scenario, M68,M69,M70) -> 0.70252732 | N67: =CHOOSE(scenario, N68,N69,N70) -> 0.66207346 | O67: =CHOOSE(scenario, O68,O69,O70) -> 0.66873037
B68: Bear Case | K68: =N18 -> 0.635 | L68: =K68+($O$68-$K$68)/($O$1-$K$1) -> 0.65375 | M68: =L68+($O$68-$K$68)/($O$1-$K$1) -> 0.6725 | N68: =M68+($O$68-$K$68)/($O$1-$K$1) -> 0.69125 | O68: =N19 -> 0.71
B69: Street Case | K69: =K35 -> 0.6624936 | L69: =L35 -> 0.6853768 | M69: =M35 -> 0.70252732 | N69: =N35 -> 0.66207346 | O69: =O35 -> 0.66873037
B70: Bullish Case | K70: =W18 -> 0.682 | L70: =K70+($O$70-$K$70)/($O$1-$K$1) -> 0.6975 | M70: =L70+($O$70-$K$70)/($O$1-$K$1) -> 0.713 | N70: =M70+($O$70-$K$70)/($O$1-$K$1) -> 0.7285 | O70: =W19 -> 0.744
B72: EBIT | F72: 6195 | G72: 5633 | H72: 6954 | I72: 10292 | J72: 13419 | K72: =K60*K73 -> 16298 | L72: =L60*L73 -> 20107.756 | M72: =M60*M73 -> 24002.512 | N72: =N60*N73 -> 23994.574 | O72: =O60*O73 -> 26785.692
B73: % sales | F73: =F72/F$31 -> 0.20859991 | G73: =G72/G$31 -> 0.17816928 | H73: =H72/H$31 -> 0.20620941 | I73: =I72/I$31 -> 0.26473236 | J73: =J72/J$31 -> 0.29639528 | K73: =CHOOSE(scenario, K74,K75,K76) -> 0.31303119 | L73: =CHOOSE(scenario, L74,L75,L76) -> 0.34026795 | M73: =CHOOSE(scenario, M74,M75,M76) -> 0.36265703 | N73: =CHOOSE(scenario, N74,N75,N76) -> 0.32808786 | O73: =CHOOSE(scenario, O74,O75,O76) -> 0.33601101
B74: Bear Case | K74: =N20 -> 0.23082125 | L74: =K74+($O$74-$K$74)/($O$1-$K$1) -> 0.25311594 | M74: =K74+($O$74-$K$74)/($O$1-$K$1) -> 0.25311594 | N74: =K74+($O$74-$K$74)/($O$1-$K$1) -> 0.25311594 | O74: =N21 -> 0.32
B75: Street Case | K75: =K38 -> 0.31303119 | L75: =L38 -> 0.34026795 | M75: =M38 -> 0.36265703 | N75: =N38 -> 0.32808786 | O75: =O38 -> 0.33601101
B76: Bullish Case | K76: =W20 -> 0.325 | L76: =K76+($O$76-$K$76)/($O$1-$K$1) -> 0.33875 | M76: =L76+($O$76-$K$76)/($O$1-$K$1) -> 0.3525 | N76: =M76+($O$76-$K$76)/($O$1-$K$1) -> 0.36625 | O76: =W21 -> 0.38
B78: Taxes | F78: 724 | G78: 772 | H78: 797 | I78: 1254 | J78: 1741 | K78: =K72*K79 -> 2021.3167 | L78: =L72*L79 -> 2522.5817 | M78: =M72*M79 -> 2955.5227 | N78: =N72*N79 -> 2995.4492 | O78: =O72*O79 -> 3359.9407
B79: % tax rate | F79: 0.11686844 | G79: 0.13704953 | H79: 0.1146103 | I79: 0.12184221 | J79: 0.12974141 | K79: =AVERAGE(F79:J79) -> 0.12402238 | L79: =AVERAGE(G79:K79) -> 0.12545316 | M79: =AVERAGE(H79:L79) -> 0.12313389 | N79: =AVERAGE(I79:M79) -> 0.12483861 | O79: =AVERAGE(J79:N79) -> 0.12543789
B81: EBIAT (or NOPAT) | F81: =F72-F78 -> 5471 | G81: =G72-G78 -> 4861 | H81: =H72-H78 -> 6157 | I81: =I72-I78 -> 9038 | J81: =J72-J78 -> 11678 | K81: =K72-K78 -> 14276.683 | L81: =L72-L78 -> 17585.175 | M81: =M72-M78 -> 21046.989 | ... O81: =O72-O78 -> 23425.751
B82: % of sales | F82: =F81/F60 -> 0.18422116 | G82: =G81/G60 -> 0.15375127 | H82: =H81/H60 -> 0.18257569 | I82: =I81/I60 -> 0.23247679 | J82: =J81/J60 -> 0.25794054 | K82: =K81/K60 -> 0.27420831 | L82: =L81/L60 -> 0.29758026 | M82: =M81/M60 -> 0.31800166 | ... O82: =O81/O60 -> 0.2938625
B84: Plus: D&A | F84: =F46 -> 12439 | G84: =G46 -> 14363 | H84: =H46 -> 14554 | I84: =I46 -> 15630 | J84: =J46 -> 16756 | K84: =K66-K72 -> 18194.795 | L84: =L66-L72 -> 20393.824 | M84: =M66-M72 -> 22494.368 | N84: =N66-N72 -> 24425.902 | O84: =O66-O72 -> 26523.293
B85: % sales | F85: =F84/F60 -> 0.41884975 | G85: =G84/G60 -> 0.45429529 | H85: =H84/H60 -> 0.43157489 | I85: =I84/I60 -> 0.40203719 | J85: =J84/J60 -> 0.37010205 | K85: =K84/K60 -> 0.34946241 | L85: =L84/L60 -> 0.34510885 | M85: =M84/M60 -> 0.33987028 | ... O85: =O84/O60 -> 0.33271936
B87: Minus: CapEx | F87: =F50 -> -552 | G87: =G50 -> -408 | H87: =H50 -> -349 | I87: =I50 -> -440 | J87: =J50 -> -688 | K87: =K88*K60 -> -913 | L87: =L88*L60 -> -1181.8778 | M87: =M88*M60 -> -1323.7031 | N87: =N88*N60 -> -1097.0189 | O87: =O88*O60 -> -956.60052
B88: % sales | F88: =F87/F60 -> -0.01858711 | G88: =G87/G60 -> -0.012904858 | H88: =H87/H60 -> -0.01034902 | I88: =I87/I60 -> -0.011317746 | J88: =J87/J60 -> -0.01519636 | K88: =CHOOSE(scenario,K89,K90,K91) -> -0.017535739 | L88: =CHOOSE(scenario,L89,L90,L91) -> -0.02 | M88: =CHOOSE(scenario,M89,M90,M91) -> -0.02 | N88: =CHOOSE(scenario,N89,N90,N91) -> -0.015 | O88: =CHOOSE(scenario,O89,O90,O91) -> -0.012
B89: Bear Case | K89: =-$N$22 -> -0.02 | L89: =-$N$22 -> -0.02 | M89: =-$N$22 -> -0.02 | N89: =-$N$22 -> -0.02 | O89: =-$N$22 -> -0.02
B90: Street Case | K90: =-$K$51 -> -0.017535739 | L90: =L51 -> -0.02 | M90: =M51 -> -0.02 | N90: =N51 -> -0.015 | O90: =O51 -> -0.012
B91: Bullish Case | K91: =-$W$22 -> -0.015 | L91: =-$W$22 -> -0.015 | M91: =-$W$22 -> -0.015 | N91: =-$W$22 -> -0.015 | O91: =-$W$22 -> -0.015
B93: Minus: Additions to Content Assets | F93: -17702 | G93: -16839 | H93: -12555 | I93: -16224 | J93: -17096 | K93: =K94*K60 -> -19524.412 | L93: =L94*L60 -> -21790.871 | M93: =M94*M60 -> -23992.119 | N93: =N94*N60 -> -26054.2 | O93: =O94*O60 -> -27900.849
B94: % sales | F94: =F93/F60 -> -0.59606708 | G94: =G93/G60 -> -0.53261007 | H94: =H93/H60 -> -0.37229784 | I94: =I93/I60 -> -0.41731615 | J94: =J93/J60 -> -0.37761187 | K94: =CHOOSE(scenario,K95,K96,K97) -> -0.375 | L94: =CHOOSE(scenario,L95,L96,L97) -> -0.36875 | M94: =CHOOSE(scenario,M95,M96,M97) -> -0.3625 | N94: =CHOOSE(scenario,N95,N96,N97) -> -0.35625 | O94: =CHOOSE(scenario,O95,O96,O97) -> -0.35
B95: Bear Case | K95: =$N$23 -> -0.38907529 | L95: =K95+(O95-K95)*(L1-K1)/(O1-K1) -> -0.38680647 | M95: =K95+(O95-K95)*(M1-K1)/(O1-K1) -> -0.38453764 | N95: =K95+(O95-K95)*(N1-K1)/(O1-K1) -> -0.38226882 | O95: =$N$24 -> -0.38
B96: Street Case | K96: =$R$23 -> -0.375 | L96: =K96+(O96-K96)*(L1-K1)/(O1-K1) -> -0.36875 | M96: =K96+(O96-K96)*(M1-K1)/(O1-K1) -> -0.3625 | N96: =K96+(O96-K96)*(N1-K1)/(O1-K1) -> -0.35625 | O96: =$R$24 -> -0.35
B97: Bullish Case | K97: =$W$23 -> -0.38907529 | L97: =K97+(O97-K97)*(L1-K1)/(O1-K1) -> -0.37430647 | M97: =K97+(O97-K97)*(M1-K1)/(O1-K1) -> -0.35953764 | N97: =K97+(O97-K97)*(N1-K1)/(O1-K1) -> -0.34476882 | O97: =$W$24 -> -0.33
B99: Minus: Change in Content Liabilities | F99: 232.9 | G99: 179.3 | H99: -585.6 | I99: -779.1 | J99: -610.8 | K99: =J99+(J99*K61) -> -702.42 | L99: =K99+(K99*L61) -> -797.2467 | M99: =L99+(L99*M61) -> -892.9163 | N99: =M99+(M99*N61) -> -986.67252 | O99: =N99+(N99*O61) -> -1075.473
B100: % sales | F100: =F99/F60 -> 0.0078422789 | G100: =G99/G60 -> 0.0056711791 | H100: =H99/H60 -> -0.017365003 | I100: =I99/I60 -> -0.020040127 | J100: =J99/J60 -> -0.013491187 | K100: =K99/K60 -> -0.013491187 | L100: =L99/L60 -> -0.013491187 | M100: =M99/M60 -> -0.013491187 | ... O100: =O99/O60 -> -0.013491187
B102: Minus: Change in WC | G102: =G53 -> 1754 | H102: =H53 -> -278 | I102: =I53 -> 1288 | J102: =J53 -> -306 | K102: =K103*K60 -> 686.51172 | L102: =L103*L60 -> 189.89215 | M102: =M103*M60 -> 542.68646 | N102: =N103*N60 -> 417.33953 | O102: =O103*O60 -> 554.2694
B103: % sales | G103: =G102/G60 -> 0.055478239 | H103: =H102/H60 -> -0.0082436319 | I103: =I102/I60 -> 0.033130128 | J103: =J102/J60 -> -0.0067588461 | K103: =AVERAGE(I103:J103) -> 0.013185641 | L103: =AVERAGE(J103:K103) -> 0.0032133975 | M103: =AVERAGE(K103:L103) -> 0.0081995193 | N103: =AVERAGE(L103:M103) -> 0.0057064584 | O103: =AVERAGE(M103:N103) -> 0.0069529888
B105: Unlevered FCF | K105: =K81+K84+K87-K102+K93+K99 -> 10645.134 | L105: =L81+L84+L87+(-L102)+L93+L99 -> 14019.111 | M105: =M81+M84+M87+(-M102)+M93+M99 -> 16789.932 | N105: =N81+N84+N87+(-N102)+N93+N99 -> 16869.795 | O105: =O81+O84+O87-O102+O93+O99 -> 19461.853
B107: Stub | K107: =YEARFRAC(C7,C8) -> 0.35555556
B108: Discount Period | K108: =K107/2 -> 0.17777778 | L108: =K108+0.5 -> 0.67777778 | M108: =L108+1 -> 1.6777778 | N108: =M108+1 -> 2.6777778 | O108: =N108+1 -> 3.6777778
B110: Discounted UFCF | K110: =(K105*K107)/(1+$C$17)^K108 -> 3731.5699 | L110: =L105/(1+$C$17)^L108 -> 13280.323 | M110: =M105/(1+$C$17)^M108 -> 14684.107 | N110: =N105/(1+$C$17)^N108 -> 13621.308 | O110: =O105/(1+$C$17)^O108 -> 14507.868
B112: Terminal Value | O112: =O105*(1+$C$18)/(C17-C18) -> 343036.28
B113: Discounted Terminal Value | O113: =O112/(1+C17)^O108 -> 255716.92
B115: Enterprise Value | O115: =O113+SUM(K110:O110) -> 315542.1
B116: Plus: Cash | O116: 9034
B117: Minus: Debt | O117: =-D -> -15363
B118: Equity Value | O118: =SUM(O115:O117) -> 309213.1
B119: Shares Outstanding | O119: 4249
B121: Price Per Share | O121: =O118/O119 -> 72.773146

Sheet WACC
B2: WACC Calculation
A4: X | B4: Inputs | F4: WACC = [Re*(E/D+E)]+[Rd*(1-t )*(D/D+E)]
B6: Re | E6: =(Rf+B_eq*MRP) -> 0.085785952
B7: Beta Equity | E7: =D31 -> 0.86964019
B8: Risk Free Rate | E8: 0.047
B9: MRP | E9: 0.0446
B11: E | E11: 331410
B12: D | E12: 15363
B13: E/D+E | E13: =E/(D+E) -> 0.95569724
B14: D/D+E | E14: =D/(D+E) -> 0.044302757
B16: Rd | E16: =437762/14462000 -> 0.030269811
B17: 1-t | E17: =1-('DCF '!J41) -> 0.87025859
B19: WACC | E19: =Re*equity_ratio+Rd*tax_shield*debt_ratio -> 0.083152446
J20: =levB / (1+(1-taxR) * (D/E)
B22: Beta
B24: Company Name | D24: Lev Beta | E24: Market Cap | F24: Net Debt | G24: Tax Rate | H24: UnLev Beta
B25: Walt Disney | D25: 1.39 | E25: 187130 | F25: =38166+7257-5695 -> 39728 | G25: =-11.9% -> -0.119 | H25: =D25/(1+(1-G25)*(F25/E25)) -> 1.1231729
B26: Warner Bros | D26: 1.57 | E26: 71579 | F26: =32845-4570 -> 28275 | G26: 0.21 | H26: =D26/(1+(1-G26)*(F26/E26)) -> 1.1965877
B27: Paramount | D27: 1.47 | E27: 11583 | F27: =13225+433-3274 -> 10384 | G27: =AVERAGE(1%,1.2%,0.3%,2.7%) -> 0.013 | H27: =D27/(1+(1-G27)*(F27/E27)) -> 0.7799104
B28: ComCast | D28: 0.65 | E28: 95281 | F28: =92979+5958-9481 -> 89456 | G28: 0.237 | H28: =D28/(1+(1-G28)*(F28/E28)) -> 0.37870975
B30: Industry Average Ulbeta | D30: =AVERAGE(H25:H28) -> 0.86959518
B31: NFLX Lev Beta | D31: =D30*(1+(1-16.8%)*(E13/E12)) -> 0.86964019 | J31: unlevB * (1+(1-taxR) * (D/E))

Sheet IS
A1: Fiscal year is January-December. All values USD Millions. | B1: 2025 | C1: 2024 | D1: 2023 | E1: 2022 | F1: 2021
A2: Sales/Revenue | B2: 45274 | C2: 38877 | D2: 33723 | E2: 31616 | F2: 29698
A3: Sales Growth | B3: 0.1646 | C3: 0.1528 | D3: 0.0667 | E3: 0.0646 | F3: -
A4: Cost of Goods Sold (COGS) incl. D&A | B4: 23274 | C4: 21040 | D4: 19715 | E4: 19168 | F4: 17333
A5: COGS excluding D&A | B5: 6518 | C5: 5410 | D5: 5161 | E5: 4805 | F5: 4894
A6: Depreciation & Amortization Expense | B6: 16756 | C6: 15630 | D6: 14554 | E6: 14363 | F6: 12439
A7: COGS Growth | B7: 0.1062 | C7: 0.0672 | D7: 0.0285 | E7: 0.1059 | F7: -
A8: Gross Income | B8: 22000 | C8: 17837 | D8: 14008 | E8: 12447 | F8: 12365
A9: Gross Income Growth | B9: 0.2334 | C9: 0.2733 | D9: 0.1254 | E9: 0.0066 | F9: -
A10: Gross Profit Margin | B10: 0.4859 | C10: - | D10: - | E10: - | F10: -
A11: SG&A Expense | B11: 8581 | C11: 7545 | D11: 7054 | E11: 6814 | F11: 6171
A12: Research & Development | B12: 3391 | C12: 2925 | D12: 2676 | E12: 2711 | F12: 2274
A13: Other SG&A | B13: 5190 | C13: 4620 | D13: 4378 | E13: 4103 | F13: 3897
A14: SGA Growth | B14: 0.1373 | C14: 0.0696 | D14: 0.0351 | E14: 0.1043 | F14: -
A15: EBIT | B15: 13419 | C15: 10292 | D15: 6954 | E15: 5633 | F15: 6195
A16: Non Operating Income/Expense | B16: 80 | C16: 392 | D16: -49 | E16: 337 | F16: 411
A18: Interest Expense | B18: 777 | C18: 719 | D18: 700 | E18: 706 | F18: 766
A19: Interest Expense Growth | B19: 0.0804 | C19: 0.027 | D19: -0.009 | E19: -0.0776 | F19: -
A21: Gross Interest Expense | B21: 777 | C21: 719 | D21: 700 | E21: 706 | F21: 766
A22: Pretax Income | B22: 12723 | C22: 9966 | D22: 6205 | E22: 5264 | F22: 5840
A23: Pretax Income Growth | B23: 0.2766 | C23: 0.606 | D23: 0.1789 | E23: -0.0987 | F23: -
A25: Pretax Margin | B25: 0.281 | C25: - | D25: - | E25: - | F25: -
A26: Income Tax | B26: 1741 | C26: 1254 | D26: 797 | E26: 772 | F26: 724
A27: Income Tax - Current Domestic | B27: 1629 | C27: 1308 | D27: 1036 | E27: 230 | F27: 167
A28: Income Tax - Current Foreign | B28: 562 | C28: 537 | D28: 305 | E28: 677 | F28: 357
A29: Income Tax - Deferred Domestic | B29: -190 | C29: -562 | D29: -468 | E29: -83 | F29: 186
A31: Income Tax - Deferred Foreign | B31: -260 | C31: -29 | D31: -75 | E31: -51 | F31: 13
A33: Consolidated Net Income | B33: 10981 | C33: 8712 | D33: 5408 | E33: 4492 | F33: 5116
A34: Net Income | B34: 10981 | C34: 8712 | D34: 5408 | E34: 4492 | F34: 5116
A35: Net Income Growth | B35: 0.2605 | C35: 0.6109 | D35: 0.2039 | E35: -0.122 | F35: -
A37: Net Margin | B37: 0.2425 | C37: - | D37: - | E37: - | F37: -
A38: Net Income After Extraordinaries | B38: 10981 | C38: 8712 | D38: 5408 | E38: 4492 | F38: 5116
A39: Net Income Available to Common | B39: 10981 | C39: 8712 | D39: 5408 | E39: 4492 | F39: 5116
A40: EPS (Basic) | B40: 2.53 | C40: 1.98 | D40: 1.2 | E40: 1 | F40: 1.12
A41: EPS (Basic) Growth | B41: 0.2747 | C41: 0.6484 | D41: 0.2087 | E41: -0.114 | F41: -
A43: Basic Shares Outstanding | B43: 4250 | C43: 4295 | D43: 4416 | E43: 4447 | F43: 4432
A44: EPS (Diluted) | B44: 2.53 | C44: 1.98 | D44: 1.2 | E44: 1 | F44: 1.12
A45: EPS (Diluted) Growth | B45: 0.2747 | C45: 0.6484 | D45: 0.2087 | E45: -0.1141 | F45: -
A47: Diluted Shares Outstanding | B47: 4344 | C47: 4393 | D47: 4495 | E47: 4513 | F47: 4554
A48: EBITDA | B48: 30175 | C48: 25922 | D48: 21508 | E48: 19996 | F48: 18633
A49: EBITDA Growth | B49: 0.164 | C49: 0.2052 | D49: 0.0757 | E49: 0.0731 | F49: -
A50: EBITDA Margin | B50: 0.6665 | C50: - | D50: - | E50: - | F50: -
A51: EBIT | B51: 13419 | C51: 10292 | D51: 6954 | E51: 5633 | F51: 6195

Sheet BS
A1: Assets
A3: Fiscal year is January-December. All values USD Millions. | B3: 2025 | C3: 2024 | D3: 2023 | E3: 2022 | F3: 2021
A4: Cash & Short Term Investments | B4: 9068 | C4: 9586 | D4: 7139 | E4: 6058 | F4: 6028
A5: Cash Only | B5: 8473 | C5: 7543 | D5: 6914 | E5: 5147 | F5: 6028
A6: Cash & Short Term Investments Growth | B6: -0.0541 | C6: 0.3427 | D6: 0.1784 | E6: 0.0051 | F6: -
A8: Cash & ST Investments / Total Assets | B8: 0.1631 | C8: 0.1744 | D8: 0.1435 | E8: 0.1247 | F8: 0.1352
A9: Total Accounts Receivable | B9: 2583 | C9: 1988 | D9: 1842 | E9: 989 | F9: 1718
A10: Accounts Receivables, Net | B10: 2031 | C10: 1335 | D10: 1287 | E10: 989 | F10: 804
A11: Accounts Receivables, Gross | B11: 2031 | C11: 1335 | D11: 1287 | E11: 989 | F11: 804
A12: Other Receivables | B12: 552 | C12: 653 | D12: 555 | E12: - | F12: 914
A13: Accounts Receivable Growth | B13: 0.2993 | C13: 0.0794 | D13: 0.8627 | E13: -0.4245 | F13: -
A15: Accounts Receivable Turnover | B15: 17.52 | C15: 19.55 | D15: 18.31 | E15: 31.97 | F15: 17.28
A16: Other Current Assets | B16: 1369 | C16: 1526 | D16: 937 | E16: 2219 | F16: 324
A17: Prepaid Expenses | B17: 498 | C17: 432 | D17: 409 | E17: 393 | F17: 324
A18: Miscellaneous Current Assets | B18: 871 | C18: 1094 | D18: 528 | E18: 1826 | F18: -
A19: Total Current Assets | B19: 13020 | C19: 13100 | D19: 9918 | E19: 9266 | F19: 8070
A20: Net Property, Plant & Equipment | B20: 4212 | C20: 3696 | D20: 3568 | E20: 3625 | F20: 3770
A21: Property, Plant & Equipment - Gross | B21: 5308 | C21: 4614 | D21: 4423 | E21: 4379 | F21: 4386
A22: Buildings | B22: 537 | C22: 476 | D22: 151 | E22: 52 | F22: 48
A23: Land & Improvements | B23: 156 | C23: 85 | D23: 88 | E23: 85 | F23: 82
A24: Machinery & Equipment | B24: 31 | C24: 15 | D24: 10 | E24: 27 | F24: 32
A25: Construction in Progress | B25: 285 | C25: 228 | D25: 406 | E25: 236 | F25: 282
A26: Computer Software and Equipment | B26: 572 | C26: 446 | D26: 414 | E26: 443 | F26: 380
A27: Transportation Equipment | B27: 99 | C27: 99 | D27: 99 | E27: 116 | F27: 111
A28: Other Property, Plant & Equipment | B28: 1421 | C28: 1162 | D28: 1177 | E28: 1194 | F28: 1003
A29: Accumulated Depreciation | B29: 1097 | C29: 918 | D29: 855 | E29: 754 | F29: 616
A30: Total Investments and Advances | B30: 89 | C30: 407 | D30: 5 | E30: 20 | F30: 24
... A35: Total Assets | B35: 55597 | C35: 54968 | D35: 49768 | E35: 48595 | F35: 44585
A36: Assets - Total - Growth | B36: 0.0114 | C36: 0.1045 | D36: 0.0241 | E36: 0.0899 | F36: -
A37: Asset Turnover | B37: 0.82 | C37: - | D37: - | E37: - | F37: -
A38: Return On Average Assets | B38: 0.1986 | C38: - | D38: - | E38: - | F38: -
A40: Liabilities & Shareholders' Equity
A42: All values USD Millions. | B42: 2025 | C42: 2024 | D42: 2023 | E42: 2022 | F42: 2021
A43: ST Debt & Current Portion LT Debt | B43: 1459 | C43: 2213 | D43: 783 | E43: 356 | F43: 1015
A44: Short Term Debt | B44: 1459 | C44: 2213 | D44: 783 | E44: 356 | F44: 1015
A45: Accounts Payable | B45: 901 | C45: 900 | D45: 747 | E45: 672 | F45: 837
A46: Accounts Payable Growth | B46: 0.0008 | C46: 0.204 | D46: 0.113 | E46: -0.1982 | F46: -
A48: Other Current Liabilities | B48: 8621 | C48: 7643 | D48: 7330 | E48: 6903 | F48: 6636
A49: Miscellaneous Current Liabilities | B49: 8621 | C49: 7643 | D49: 7330 | E49: 6903 | F49: 6636
A50: Total Current Liabilities | B50: 10981 | C50: 10755 | D50: 8861 | E50: 7931 | F50: 8489
A51: Current Ratio | B51: 1.19 | C51: 1.22 | D51: 1.12 | E51: 1.17 | F51: 0.95
A52: Quick Ratio | B52: 1.19 | C52: 1.22 | D52: 1.12 | E52: 1.17 | F52: 0.95
A53: Cash Ratio | B53: 0.83 | C53: 0.89 | D53: 0.81 | E53: 0.76 | F53: 0.71
A54: Long-Term Debt | B54: 15516 | C54: 15782 | D54: 16190 | E54: 16576 | F54: 17102
A55: Long-Term Debt excl. Capitalized Leases | B55: 15516 | C55: 15782 | D55: 16190 | E55: 16576 | F55: 17102
A56: Non-Convertible Debt | B56: 13464 | C56: 13798 | D56: 14143 | E56: 14353 | F56: 14693
A57: Provision for Risks & Charges | B57: - | C57: 432 | D57: 327 | E57: 227 | F57: 203
A58: Deferred Taxes | B58: -1955 | C58: -1178 | D58: -875 | E58: -262 | F58: -148
A60: Deferred Taxes - Credit | B60: 107 | C60: 1338 | D60: 1036 | E60: - | F60: -
A61: Deferred Taxes - Debit | B61: 2062 | C61: 2515 | D61: 1910 | E61: 262 | F61: 148
A62: Other Liabilities | B62: 2377 | C62: 1917 | D62: 2766 | E62: 3084 | F62: 2942
A63: Other Liabilities (excl. Deferred Income) | B63: 2377 | C63: 1917 | D63: 2766 | E63: 3084 | F63: 2942
A64: Total Liabilities | B64: 28982 | C64: 30225 | D64: 29179 | E64: 27817 | F64: 28735
A65: Total Liabilities / Total Assets | B65: 0.5213 | C65: 0.5499 | D65: 0.5863 | E65: 0.5724 | F65: 0.6445
A66: Common Equity (Total) | B66: 26615 | C66: 24744 | D66: 20588 | E66: 20777 | F66: 15849
A67: Common Stock Par/Carry Value | B67: 7286 | C67: 6252 | D67: 5145 | E67: 4638 | F67: 4025
A68: Retained Earnings | B68: 42282 | C68: 31301 | D68: 22589 | E68: 17181 | F68: 12689
A69: Cumulative Translation Adjustment/Unrealized For. Exch. Gain | B69: -194 | C69: -377 | D69: -104 | E69: -217 | F69: -40
A71: Unrealized Gain/Loss Marketable Securities | B71: - | C71: 3 | D71: - | E71: - | F71: -
A72: Other Appropriated Reserves | B72: -387 | C72: 736 | D72: -120 | E72: - | F72: -
A74: Treasury Stock | B74: -22373 | C74: -13172 | D74: -6922 | E74: -824 | F74: -824
A76: Common Equity / Total Assets | B76: 0.4787 | C76: 0.4501 | D76: 0.4137 | E76: 0.4276 | F76: 0.3555
A77: Total Shareholders' Equity | B77: 26615 | C77: 24744 | D77: 20588 | E77: 20777 | F77: 15849
A78: Total Shareholders' Equity / Total Assets | B78: 0.4787 | C78: 0.4501 | D78: 0.4137 | E78: 0.4276 | F78: 0.3555
A79: Total Equity | B79: 26615 | C79: 24744 | D79: 20588 | E79: 20777 | F79: 15849
A80: Liabilities & Shareholders' Equity | B80: 55597 | C80: 54968 | D80: 49768 | E80: 48595 | F80: 44585

Sheet CF
A1: Operating Activities
A3: Fiscal year is January-December. All values USD Millions. | B3: 2025 | C3: 2024 | D3: 2023 | E3: 2022 | F3: 2021
A4: Net Income before Extraordinaries | B4: 10981 | C4: 8712 | D4: 5408 | E4: 4492 | F4: 5116
A5: Net Income Growth | B5: 0.2605 | C5: 0.6109 | D5: 0.2039 | E5: -0.122 | F5: -
A7: Depreciation, Depletion & Amortization | B7: 16756 | C7: 15630 | D7: 14554 | E7: 14363 | F7: 12439
A8: Deferred Taxes & Investment Tax Credit | B8: -442 | C8: -591 | D8: -459 | E8: -167 | F8: 200
A10: Deferred Taxes | B10: -442 | C10: -591 | D10: -459 | E10: -167 | F10: 200
A12: Other Funds | B12: -16689 | C12: -16357 | D12: -12113 | E12: -15904 | F12: -17120
A14: Funds from Operations | B14: 10605 | C14: 7394 | D14: 7390 | E14: 2784 | F14: 635
A15: Changes in Working Capital | B15: -456 | C15: -33 | D15: -116 | E15: -758 | F15: -242
A17: Accounts Payable | B17: -8 | C17: 121 | D17: 94 | E17: -159 | F17: 145
A19: Other Accruals | B19: 881 | C19: 192 | D19: 104 | E19: -56 | F19: 180
A21: Other Assets/Liabilities | B21: -1329 | C21: -346 | D21: -313 | E21: -544 | F21: -567
A23: Net Operating Cash Flow | B23: 10149 | C23: 7361 | D23: 7274 | E23: 2026 | F23: 393
A24: Net Operating Cash Flow Growth | B24: 0.3787 | C24: 0.012 | D24: 2.59 | E24: 4.161 | F24: -
A25: Net Operating Cash Flow / Sales | B25: 0.2242 | C25: 0.1894 | D25: 0.2157 | E25: 0.0641 | F25: 0.0132
A27: Investing Activities
A29: All values USD Millions. | B29: 2025 | C29: 2024 | D29: 2023 | E29: 2022 | F29: 2021
A30: Capital Expenditures | B30: -688 | C30: -440 | D30: -349 | E30: -408 | F30: -552
A32: Capital Expenditures (Fixed Assets) | B32: -688 | C32: -440 | D32: -349 | E32: -408 | F32: -525
A34: Capital Expenditures (Other Assets) | B34: - | C34: - | D34: - | E34: - | F34: -27
A36: Capital Expenditures Growth | B36: -0.5658 | C36: -0.261 | D36: 0.1451 | E36: 0.2607 | F36: -
A38: Capital Expenditures / Sales | B38: -0.0152 | C38: -0.0113 | D38: -0.0103 | E38: -0.0129 | F38: -0.0186
A40: Purchase/Sale of Investments | B40: 1747 | C40: -1742 | D40: 890 | E40: -911 | F40: -
A42: Purchase of Investments | B42: -170 | C42: -1742 | D42: -505 | E42: -911 | F42: -
A44: Sale/Maturity of Investments | B44: 1917 | C44: - | D44: 1395 | E44: - | F44: -
A45: Other Uses | B45: -17 | C45: - | D45: - | E45: -757 | F45: -788
A47: Net Investing Cash Flow | B47: 1042 | C47: -2182 | D47: 542 | E47: -2076 | F47: -1340
A49: Net Investing Cash Flow Growth | B49: 1.4774 | C49: -5.0273 | D49: 1.2609 | E49: -0.5497 | F49: -
A51: Net Investing Cash Flow / Sales | B51: 0.023 | C51: -0.0561 | D51: 0.0161 | E51: -0.0657 | F51: -0.0451
A54: Financing Activities
A56: All values USD Millions. | B56: 2025 | C56: 2024 | D56: 2023 | E56: 2022 | F56: 2021 | G56: 5-year trend
A57: Change in Capital Stock | B57: -8460 | C57: -5431 | D57: -5875 | E57: 36 | F57: -426
A59: Repurchase of Common & Preferred Stk. | B59: -9127 | C59: -6264 | D59: -6045 | E59: - | F59: -600
A61: Sale of Common & Preferred Stock | B61: 667 | C61: 833 | D61: 170 | E61: 36 | F61: 174
A62: Proceeds from Stock Options | B62: 667 | C62: 833 | D62: 170 | E62: 36 | F62: 174
A63: Issuance/Reduction of Debt, Net | B63: -1833 | C63: 1394 | D63: - | E63: -700 | F63: -500
A65: Change in Long-Term Debt | B65: -1833 | C65: 1394 | D65: - | E65: -700 | F65: -500
A67: Issuance of Long-Term Debt | B67: - | C67: 1794 | D67: - | E67: - | F67: -
A68: Reduction in Long-Term Debt | B68: -1833 | C68: -400 | D68: - | E68: -700 | F68: -500
A70: Other Funds | B70: -52 | C70: -38 | D70: -75 | E70: - | F70: -224
A72: Other Uses | B72: -52 | C72: -38 | D72: -75 | E72: - | F72: -224
A74: Net Financing Cash Flow | B74: -10346 | C74: -4074 | D74: -5951 | E74: -664 | F74: -1150
A76: Net Financing Cash Flow Growth | B76: -1.5392 | C76: 0.3153 | D76: -7.9586 | E76: 0.4223 | F76: -
A78: Net Financing Cash Flow / Sales | B78: -0.2285 | C78: -0.1048 | D78: -0.1765 | E78: -0.021 | F78: -0.0387
A80: Exchange Rate Effect | B80: 387 | C80: -416 | D80: 83 | E80: -170 | F80: -87
A82: Net Change in Cash | B82: 1232 | C82: 689 | D82: 1948 | E82: -885 | F82: -2184
A84: Free Cash Flow | B84: 9461 | C84: 6922 | D84: 6926 | E84: 1619 | F84: -132
A86: Free Cash Flow Growth | B86: 0.3668 | C86: -0.0006 | D86: 3.279 | E86: 13.2639 | F86: -
A88: Free Cash Flow Yield | B88: 0.0232 | C88: - | D88: - | E88: - | F88: -

Sheet Q2
A1: Netflix, Inc.
A2: Consolidated Statements of Operations
A3: (unaudited)
A4: (in thousands, except per share data)
E5: Three Months Ended | I5: Twelve Months Ended | J5: Three Months Ended | L5: Six Months Ended
E6: March 31, | F6: June 30, | G6: September 30, | H6: December 31, | I6: December 31, | J6: March 31, | K6: June 30, | L6: June 30,
E7: 2025 | F7: 2025 | G7: 2025 | H7: 2025 | I7: 2025 | J7: 2026 | K7: 2026 | L7: 2026
A9: Revenues | E9: $ 10,542,801 | F9: $ 11,079,166 | G9: $ 11,510,307 | H9: $ 12,050,762 | I9: $ 45,183,036 | J9: $ 12,249,757 | K9: $ 12,559,938 | L9: $ 24,809,695 | N9: =O9*2 -> 49619390 | O9: 24809695
B10: Cost of revenues | E10: 5263147 | F10: 5325311 | G10: 6164250 | H10: 6522621 | I10: 23275329 | J10: 5888238 | K10: 6036965 | L10: 11925203
B11: Sales and marketing | E11: 688370 | F11: 713265 | G11: 786295 | H11: 1113376 | I11: 3301306 | J11: 842217 | K11: 823838 | L11: 1666055
B12: Technology and development | E12: 822823 | F12: 824683 | G12: 853584 | H12: 890300 | I12: 3391390 | J12: 959696 | K12: 1007675 | L12: 1967371
B13: General and administrative | E13: 421462 | F13: 441213 | G13: 457931 | H13: 567802 | I13: 1888408 | J13: 602609 | K13: 498850 | L13: 1101459
A14: Operating income | E14: 3346999 | F14: 3774694 | G14: 3248247 | H14: 2956663 | I14: 13326603 | J14: 3956997 | K14: 4192610 | L14: 8149607 | N14: 8149 | O14: =N14/50% -> 16298
A15: Other income (expense):
B16: Interest expense | E16: -184172 | F16: -182649 | G16: -175294 | H16: -234395 | I16: -776510 | J16: -262077 | K16: -175685 | L16: -437762 | M16: =437762/14462000 -> 0.030269811
B17: Interest and other income (expense) | E17: 50899 | F17: 39630 | G17: 36457 | H17: 45473 | I17: 172459 | J17: 2852166 | K17: 51661 | L17: 2903827 | N17: 8149607
A18: Income before income taxes | E18: 3213726 | F18: 3631675 | G18: 3109410 | H18: 2767741 | I18: 12722552 | J18: 6547086 | K18: 4068586 | L18: 10615672 | N18: 1931467
A19: Provision for income taxes | E19: -323375 | F19: -506262 | G19: -562494 | H19: -349220 | I19: -1741351 | J19: -1264295 | K19: -667172 | L19: -1931467
A20: Net income | E20: $ 2,890,351 | F20: $ 3,125,413 | G20: $ 2,546,916 | H20: $ 2,418,521 | I20: $ 10,981,201 | J20: $ 5,282,791 | K20: $ 3,401,414 | L20: $ 8,684,205
A21: Earnings per share*:
B22: Basic | E22: $ 0.68 | F22: $ 0.74 | G22: $ 0.60 | H22: $ 0.57 | I22: $ 2.58 | J22: $ 1.25 | K22: $ 0.81 | L22: $ 2.06
B23: Diluted | E23: $ 0.66 | F23: $ 0.72 | G23: $ 0.59 | H23: $ 0.56 | I23: $ 2.53 | J23: $ 1.23 | K23: $ 0.80 | L23: $ 2.03
A24: Weighted-average shares of common stock outstanding*:
B25: Basic | E25: 4272695 | F25: 4252112 | G25: 4244553 | H25: 4229221 | I25: 4249512 | J25: 4222787 | K25: 4189303 | L25: 4205952 | N25: Sh. Out. 2025 | O25: 4250
B26: Diluted | E26: 4369623 | F26: 4348825 | G26: 4340392 | H26: 4317144 | I26: 4343863 | J26: 4298437 | K26: 4261300 | L26: 4279776
A32: Net income | G32: 2890351 | H32: 3125413 | I32: 2546916 | J32: 2418521 | K32: 10981201 | L32: 5282791 | M32: 3401414 | N32: 8684205
A33: Adjustments to reconcile net income to net cash
B34: provided by operating activities:
C35: Additions to content assets | G35: -3549657 | H35: -3835813 | I35: -4653935 | J35: -5057212 | K35: -17096617 | L35: -4846917 | M35: -4927523 | N35: -9774440
C36: Change in content liabilities | G36: -411253 | H36: -214052 | I36: 24262 | J36: -9795 | K36: -610838 | L36: 45216 | M36: -181794 | N36: -136578 | P36: 2025 | Q36: h1 | R36: h2 | S36: increase? | U36: 2026 projected | V36: h1 | W36: h2 | X36: new tot
C37: Amortization of content assets | G37: 3823112 | H37: 3832074 | I37: 4002744 | J37: 4764236 | K37: 16422166 | L37: 4217900 | M37: 4311309 | N37: 8529209 | P37: =SUM(K37:K38) -> 16755555 | Q37: =SUM(G37:H38) -> 7815266 | R37: =SUM(I37:J38) -> 8940289 | S37: =R37-Q37 -> 1125023 | V37: =SUM(N37:N38) -> 8728314 | W37: =V37*(1+10%) -> 9601145.4 | X37: =SUM(V37:W37) -> 18329459
C38: Depreciation and amortization of property, equipment and intangibles | G38: 80067 | H38: 80013 | I38: 87326 | J38: 85983 | K38: 333389 | L38: 98575 | M38: 100530 | N38: 199105 | S38: =S37/Q37 -> 0.14395198
C39: Stock-based compensation expense | G39: 71977 | H39: 80862 | I39: 80986 | J39: 134624 | K39: 368449 | L39: 140405 | M39: 131312 | N39: 271717 | P39: increase 25/26 | Q39: =SUM(X37-P37) -> 1573904.4 | R39: =Q39/X37 -> 0.085867475
C40: Foreign currency remeasurement loss (gain) on debt | G40: 28547 | H40: 55238 | I40: -1707 | J40: -9730 | K40: 72348 | L40: -10110 | M40: -8813 | N40: -18923
C41: Other non-cash items | G41: 114730 | H41: 120139 | I41: 142293 | J41: 200289 | K41: 577451 | L41: 198227 | M41: 141356 | N41: 339583
C42: Deferred income taxes | G42: -163928 | H42: -135755 | I42: 20539 | J42: -162912 | K42: -442056 | L42: 58819 | M42: 81260 | N42: 140079
C43: Changes in operating assets and liabilities:
D44: Other current assets | G44: -131367 | H44: -176683 | I44: -169597 | J44: -313014 | K44: -790661 | L44: -704640 | M44: 111713 | N44: -592927
D45: Accounts payable | G45: -276426 | H45: 11046 | I45: 139451 | J45: 117890 | K45: -8039 | L45: 154 | M45: -157397 | N45: -157243
D46: Accrued expenses and other liabilities | G46: 306413 | H46: -267235 | I46: 707151 | J46: 134889 | K46: 881218 | L46: 1295904 | M46: -1249793 | N46: 46111
D47: Deferred revenue | G47: 88913 | H47: 118635 | I47: -3686 | J47: 51055 | K47: 254917 | L47: -32282 | M47: 54008 | N47: 21726
D48: Other non-current assets and liabilities | G48: -82280 | H48: -370624 | I48: -97569 | J48: -243182 | K48: -793655 | L48: -453837 | M48: -63770 | N48: -517607
F49: Net cash provided by operating activities | G49: 2789199 | H49: 2423258 | I49: 2825174 | J49: 2111642 | K49: 10149273 | L49: 5290205 | M49: 1743812 | N49: 7034017
A51: Purchases of property and equipment | G51: -128277 | H51: -155889 | I51: -164719 | J51: -239335 | K51: -688220 | L51: -196130 | M51: -218644 | N51: -414774
A52: Acquisitions | G52: 0 | H52: 0 | I52: 0 | J52: -17194 | K52: -17194 | L52: -585744 | M52: 0 | N52: -585744
A53: Purchases of investments | G53: -156015 | H53: -1650 | I53: -3850 | J53: -8450 | K53: -169965 | L53: 0 | M53: 0 | N53: 0
A54: Proceeds from maturities and sales of investments | G54: 769954 | H54: 962413 | I54: 176250 | J54: 8450 | K54: 1917067 | L54: 0 | M54: 0 | N54: 0
A55: Other investing activities | G55: 0 | H55: -36190 | I55: 36190 | J55: 0 | K55: 0 | L55: 0 | M55: 0 | N55: 0
F56: Net cash provided by (used in) investing activities | G56: 485662 | H56: 768684 | I56: 43871 | J56: -256529 | K56: 1041688 | L56: -781874 | M56: -218644 | N56: -1000518
A58: Repayments of debt | G58: -800000 | H58: -1033450 | I58: 0 | J58: 0 | K58: -1833450 | L58: 0 | M58: 0 | N58: 0
A59: Proceeds from issuance of common stock | G59: 351602 | H59: 169066 | I59: 70215 | J59: 76082 | K59: 666965 | L59: 49310 | M59: 59980 | N59: 109290
A60: Repurchases of common stock | G60: -3536396 | H60: -1654327 | I60: -1856885 | J60: -2079559 | K60: -9127167 | L60: -1270588 | M60: -4714403 | N60: -5984991
A61: Taxes paid related to net share settlement of equity awards | G61: -27870 | H61: -6114 | I61: -6196 | J61: -5985 | K61: -46165 | L61: -29230 | M61: -6631 | N61: -35861
A62: Other financing activities | G62: -15652 | H62: 21957 | I62: 55837 | J62: -67948 | K62: -5806 | L62: 19694 | M62: -8573 | N62: 11121
F63: Net cash used in financing activities | G63: -4028316 | H63: -2502868 | I63: -1737029 | J63: -2077410 | K63: -10345623 | L63: -1230814 | M63: -4669627 | N63: -5900441
G65: 150146 | H65: 287471 | I65: -21721 | J65: -29377 | K65: 386519 | L65: -49838 | M65: -19628 | N65: -69466
G66: -603309 | H66: 976545 | I66: 1110295 | J66: -251674 | K66: 1231857 | L66: 3227679 | M66: -3164087 | N66: 63592
G67: 7807337 | H67: 7204028 | I67: 8180573 | J67: 9290868 | K67: 7807337 | L67: 9039194 | M67: 12266873 | N67: 9039194
G68: 7204028 | H68: 8180573 | I68: 9290868 | J68: 9039194 | K68: 9039194 | L68: 12266873 | M68: 9102786 | N68: 9102786
A71: Net cash provided by operating activities | G71: 2789199 | H71: 2423258 | I71: 2825174 | J71: 2111642 | K71: 10149273 | L71: 5290205 | M71: 1743812 | N71: 7034017
A72: Purchases of property and equipment | G72: -128277 | H72: -155889 | I72: -164719 | J72: -239335 | K72: -688220 | L72: -196130 | M72: -218644 | N72: -414774
A73: Non-GAAP free cash flow | G73: 2660922 | H73: 2267369 | I73: 2660455 | J73: 1872307 | K73: 9461053 | L73: 5094075 | M73: 1525168 | N73: 6619243
